<annotation>
	<folder></folder>
	<filename>d3fd9950a98d22fe_jpg.rf.afde6c28678b9c7a76ba9d31c3d4a6b4.jpg</filename>
	<path>d3fd9950a98d22fe_jpg.rf.afde6c28678b9c7a76ba9d31c3d4a6b4.jpg</path>
	<source>
		<database>roboflow.ai</database>
	</source>
	<size>
		<width>416</width>
		<height>416</height>
		<depth>3</depth>
	</size>
	<segmented>0</segmented>
	<object>
		<name>Car</name>
		<pose>Unspecified</pose>
		<truncated>0</truncated>
		<difficult>0</difficult>
		<occluded>0</occluded>
		<bndbox>
			<xmin>12</xmin>
			<xmax>405</xmax>
			<ymin>119</ymin>
			<ymax>335</ymax>
		</bndbox>
	</object>
	<object>
		<name>Car</name>
		<pose>Unspecified</pose>
		<truncated>0</truncated>
		<difficult>0</difficult>
		<occluded>0</occluded>
		<bndbox>
			<xmin>254</xmin>
			<xmax>417</xmax>
			<ymin>58</ymin>
			<ymax>202</ymax>
		</bndbox>
	</object>
</annotation>
